pymseed-0.0.5.dist-info/RECORD
pymseed-0.0.5.dist-info/WHEEL
pymseed-0.0.5.dist-info/top_level.txt
pymseed-0.0.5.dist-info/METADATA
pymseed-0.0.5.dist-info/licenses/LICENSE
pymseed/msrecord_reader.py
pymseed/definitions.py
pymseed/util.py
pymseed/__init__.py
pymseed/__version__.py
pymseed/msrecord_buffer_reader.py
pymseed/mstracelist.py
pymseed/clib.py
pymseed/_libmseed_cffi.cpython-310-darwin.so
pymseed/exceptions.py
pymseed/msrecord.py
