Metadata-Version: 2.4
Name: pymseed
Version: 0.0.5
Summary: A Python package for reading and writing miniSEED formatted data
Author-email: EarthScope Data Services <software@earthscope.org>
License-Expression: Apache-2.0
Project-URL: Homepage, https://github.com/EarthScope/pymseed
Project-URL: Repository, https://github.com/EarthScope/pymseed
Project-URL: Issues, https://github.com/EarthScope/pymseed/issues
Keywords: seismology,miniseed,mseed,data,waveform,seismic
Classifier: Development Status :: 3 - Alpha
Classifier: Intended Audience :: Science/Research
Classifier: Topic :: Scientific/Engineering
Classifier: Operating System :: MacOS :: MacOS X
Classifier: Operating System :: POSIX :: Linux
Classifier: Operating System :: POSIX :: Other
Classifier: Operating System :: Microsoft :: Windows
Classifier: Programming Language :: Python :: 3
Classifier: Programming Language :: Python :: 3.9
Classifier: Programming Language :: Python :: 3.10
Classifier: Programming Language :: Python :: 3.11
Classifier: Programming Language :: Python :: 3.12
Classifier: Programming Language :: Python :: 3.13
Classifier: Programming Language :: Python :: Implementation :: CPython
Classifier: Programming Language :: Python :: Implementation :: PyPy
Requires-Python: >=3.9
License-File: LICENSE
Requires-Dist: cffi>=1.15.0
Provides-Extra: dev
Requires-Dist: pytest>=7.0.0; extra == "dev"
Requires-Dist: pytest-cov>=4.0.0; extra == "dev"
Requires-Dist: ruff>=0.1.0; extra == "dev"
Requires-Dist: mypy>=1.0.0; extra == "dev"
Requires-Dist: pre-commit>=3.0.0; extra == "dev"
Provides-Extra: numpy
Requires-Dist: numpy>=1.21.0; extra == "numpy"
Provides-Extra: docs
Requires-Dist: sphinx>=5.0.0; extra == "docs"
Requires-Dist: sphinx-rtd-theme>=1.0.0; extra == "docs"
Requires-Dist: sphinxcontrib-napoleon>=0.7; extra == "docs"
Provides-Extra: test
Requires-Dist: pytest>=7.0.0; extra == "test"
Requires-Dist: pytest-cov>=4.0.0; extra == "test"
Requires-Dist: numpy>=1.21.0; extra == "test"
Provides-Extra: release
Requires-Dist: build>=0.10.0; extra == "release"
Requires-Dist: twine>=4.0.0; extra == "release"
Provides-Extra: all
Requires-Dist: pymseed[dev,docs,numpy,test]; extra == "all"
Dynamic: license-file
